.gitignore
LICENSE
MANIFEST.in
NOTICE
README.rst
setup.py
fserve/__init__.py
fserve/_sendfile.py
fserve/console.py
fserve/serve.py
fserve/util.py
fserve.egg-info/PKG-INFO
fserve.egg-info/SOURCES.txt
fserve.egg-info/dependency_links.txt
fserve.egg-info/entry_points.txt
fserve.egg-info/requires.txt
fserve.egg-info/top_level.txt